typeahead/__init__.py
typeahead/auto_complete.py
typeahead-0.0.9.dist-info/METADATA
typeahead-0.0.9.dist-info/WHEEL
typeahead-0.0.9.dist-info/top_level.txt
typeahead-0.0.9.dist-info/RECORD
