Metadata-Version: 2.1
Name: typeahead
Version: 0.0.9
Summary: Typeahead feature
Home-page: UNKNOWN
Author: techy_cereal 
Author-email: alexanderjmilliken@gmail.com
License: UNKNOWN
Keywords: python,typeahead,auto complete
Platform: UNKNOWN
Classifier: Development Status :: 1 - Planning
Classifier: Intended Audience :: Developers
Classifier: Programming Language :: Python :: 3
Classifier: Operating System :: Unix
Classifier: Operating System :: MacOS :: MacOS X
Classifier: Operating System :: Microsoft :: Windows
